packagefolder/__init__.py
packagefolder/__main__.py
packagefolder/simplecomponent.py
packagefolder-0.0.1.dist-info/LICENCE.txt
packagefolder-0.0.1.dist-info/METADATA
packagefolder-0.0.1.dist-info/WHEEL
packagefolder-0.0.1.dist-info/top_level.txt
packagefolder-0.0.1.dist-info/RECORD
